lssm/__init__.py
lssm/_modidx.py
lssm/callbacks.py
lssm/dataloaders.py
lssm/hooks.py
lssm/learner.py
lssm/loading.py
lssm/models.py
lssm/preprocessing.py
lssm/transforms.py
lssm/visualization.py
lssm-0.1.2.dist-info/LICENSE
lssm-0.1.2.dist-info/METADATA
lssm-0.1.2.dist-info/WHEEL
lssm-0.1.2.dist-info/entry_points.txt
lssm-0.1.2.dist-info/top_level.txt
lssm-0.1.2.dist-info/RECORD
