Metadata-Version: 2.1
Name: lssm
Version: 0.1.2
Summary: Modelling pipeline to develop and monitor Large Soil Spectral Models (LSSM)
Home-page: https://github.com/franckalbinet/lssm
Author: Franck Albinet
Author-email: franckalbinet@gmail.com
License: Apache Software License 2.0
Keywords: nbdev jupyter notebook python
Classifier: Development Status :: 4 - Beta
Classifier: Intended Audience :: Developers
Classifier: Natural Language :: English
Classifier: Programming Language :: Python :: 3.7
Classifier: Programming Language :: Python :: 3.8
Classifier: Programming Language :: Python :: 3.9
Classifier: Programming Language :: Python :: 3.10
Classifier: License :: OSI Approved :: Apache Software License
Requires-Python: >=3.7
License-File: LICENSE
Requires-Dist: tqdm
Requires-Dist: pandas
Requires-Dist: scikit-learn
Requires-Dist: seaborn
Requires-Dist: torch
Requires-Dist: torchvision
Requires-Dist: torchaudio
Requires-Dist: timm
Requires-Dist: torcheval
Requires-Dist: fastprogress
Requires-Dist: fastdownload
Requires-Dist: palettable
Provides-Extra: dev
